stringify/__init__.py
stringify/util.py
stringify/version.py
stringify-0.1.1.dist-info/DESCRIPTION.rst
stringify-0.1.1.dist-info/METADATA
stringify-0.1.1.dist-info/RECORD
stringify-0.1.1.dist-info/WHEEL
stringify-0.1.1.dist-info/metadata.json
stringify-0.1.1.dist-info/top_level.txt
