Metadata-Version: 1.1
Name: stringify
Version: 0.1.1
Summary: Automatic string encoding ofbinary files into python variables
Home-page: https://github.com/slightlynybbled/stringify
Author: Jason R. Jones
Author-email: slightlynybbled@gmail.com
License: MIT
Keywords: string base64 binary
Platform: UNKNOWN
Classifier: Development Status :: 3 - Alpha
Classifier: Programming Language :: Python :: 3
Classifier: Programming Language :: Python :: 3.5
Classifier: Programming Language :: Python :: 3.6
Classifier: Natural Language :: English
